yiban/__init__.py
yiban/Apis/Task.py
yiban/Apis/User.py
yiban/Apis/Yiban.py
yiban/Apis/__init__.py
yiban/Core/BaseReq.py
yiban/Core/EpidemicPrevention.py
yiban/Core/Login.py
yiban/Core/SchoolBased.py
yiban/Core/SchoolBasedAuth.py
yiban/Core/TaskFeedback.py
yiban/Core/__init__.py
fyiban-1.0.7.dist-info/METADATA
fyiban-1.0.7.dist-info/WHEEL
fyiban-1.0.7.dist-info/top_level.txt
fyiban-1.0.7.dist-info/RECORD
